Workbook

Sheet DD Full Checklist
D2: PROJECT TEAM KICKOFF CHECKLIST | F2: KEY DATES | H2: DAYS REMAINING | I2: Days Passed
D3: RAP UP Portfolio, Roxbury, MA | F3: LOI executed | G3: 46013 | H3: =MAX(G3-TODAY(),0) -> 0 | I3: =+MAX(TODAY()-G3,0) -> 204
F4: Seller deadline to sent DD request | G4: 46030 | H4: =MAX(G4-TODAY(),0) -> 0 | I4: =+MAX(TODAY()-G4,0) -> 187
F5: Initial Deposit ($50K) | G5: 46101 | H5: =MAX(G5-TODAY(),0) -> 0 | I5: =+MAX(TODAY()-G5,0) -> 116
F6: Rollover TS | G6: =+G5+30 -> 46131 | H6: =MAX(G6-TODAY(),0) -> 0 | I6: =+MAX(TODAY()-G6,0) -> 86
F7: End of DD / 2nd Deposit ($150K) | G7: =+G5+60 -> 46161 | H7: =MAX(G7-TODAY(),0) -> 0 | I7: =+MAX(TODAY()-G7,0) -> 56
F8: Buyer to send JV OA | G8: =+G7+30 -> 46191 | H8: =MAX(G8-TODAY(),0) -> 0 | I8: =+MAX(TODAY()-G8,0) -> 26
F9: Seller to confirm Rollover terms | G9: =+G5+105 -> 46206 | H9: =MAX(G9-TODAY(),0) -> 0 | I9: =+MAX(TODAY()-G9,0) -> 11
F10: Projected HUD Approval | G10: 46253 | H10: =MAX(G10-TODAY(),0) -> 36 | I10: =+MAX(TODAY()-G10,0) -> 0
F11: Projected Closing | G11: =+G10+30 -> 46283 | H11: =MAX(G11-TODAY(),0) -> 66 | I11: =+MAX(TODAY()-G11,0) -> 0
F12: Outside Closing Date | G12: =+G5+30*6+30 -> 46311 | H12: =MAX(G12-TODAY(),0) -> 94 | I12: =+MAX(TODAY()-G12,0) -> 0 | N12: =+TODAY() -> 46217
C14: DIV Folder | D14: Item # | E14: Action Item | F14: Status | G14: Responsible Party | H14: External Party | I14: Outside Date | J14: CC Comment | K14: Partner Comment | N14: Days Remaining
D15: Equity Financing
D16: =+MAX($D$14:D15)+1 -> 1 | E16: Create Investor log/tracker | F16: Closed | G16: PK | I16: Ongoing | M16: INTERNAL | N16: =IF(OR($F16="Closed",ISBLANK(I16)),"-",IFERROR(MAX(I16-$N$12,0),"-")) -> -
D17: =+MAX($D$14:D16)+1 -> 2 | E17: Draft initial investor email | F17: Closed | G17: PK | I17: 46027 | M17: INTERNAL | N17: =IF(OR($F17="Closed",ISBLANK(I17)),"-",IFERROR(MAX(I17-$N$12,0),"-")) -> -
D18: =+MAX($D$14:D17)+1 -> 3 | E18: Set up Smallchange account | F18: Closed | G18: PK | I18: 46082 | J18: $10k set up fee + 7% success fee | M18: INTERNAL | N18: =IF(OR($F18="Closed",ISBLANK(I18)),"-",IFERROR(MAX(I18-$N$12,0),"-")) -> -
D19: =+MAX($D$14:D18)+1 -> 4 | E19: Finalize and confirm special GP Investor roster | F19: Open | G19: PK | I19: =+G11-60 -> 46223 | J19: Discuss funding of 2% UPB. Send out this week. Drop individual signature blocks for individuals | M19: INTERNAL | N19: =IF(OR($F19="Closed",ISBLANK(I19)),"-",IFERROR(MAX(I19-$N$12,0),"-")) -> 6
D20: =+MAX($D$14:D19)+1 -> 5 | E20: Confirm special co-GP AMF approach | F20: Open | G20: BA | J20: CC internal to discuss before sending materials
D21: =+MAX($D$14:D20)+1 -> 6 | E21: Finalize Caste investment OM | F21: Open | G21: BA | I21: 46082 | J21: Update OM with latest financials/deal | M21: INTERNAL | N21: =IF(OR($F21="Closed",ISBLANK(I21)),"-",IFERROR(MAX(I21-$N$12,0),"-")) -> 0
D22: Debt Financing | N22: =IF(OR($F22="Closed",ISBLANK(I22)),"-",IFERROR(MAX(I22-$N$12,0),"-")) -> -
D23: =+MAX($D$14:D22)+1 -> 7 | E23: Draft list of prospective lenders to send materials | F23: Closed | G23: AS | I23: TBC | N23: =IF(OR($F23="Closed",ISBLANK(I23)),"-",IFERROR(MAX(I23-$N$12,0),"-")) -> -
D24: =+MAX($D$14:D23)+1 -> 8 | E24: Create Lender OM - updated Model, S+U, OM, Rent Roll | F24: Closed | G24: AS | I24: TBC | J24: Update as more recent DD materials come in | N24: =IF(OR($F24="Closed",ISBLANK(I24)),"-",IFERROR(MAX(I24-$N$12,0),"-")) -> -
D25: =+MAX($D$14:D24)+1 -> 9 | E25: Create Lender tracker | F25: Closed | G25: AS | I25: TBC | J25: See Teams | N25: =IF(OR($F25="Closed",ISBLANK(I25)),"-",IFERROR(MAX(I25-$N$12,0),"-")) -> -
D26: =+MAX($D$14:D25)+1 -> 10 | E26: Provide feedback on loan options and impacts to business plan | F26: Closed | H26: Jacques | I26: TBC | J26: Going back to NM and WD for best and final | N26: =IF(OR($F26="Closed",ISBLANK(I26)),"-",IFERROR(MAX(I26-$N$12,0),"-")) -> -
D27: =+MAX($D$14:D26)+1 -> 11 | E27: W& D UW DD CHECKLIST | F27: Open | I27: TBC | J27: Received. Send relevant items to UHM. Schedule call to discuss updated financials & A/R. | N27: =IF(OR($F27="Closed",ISBLANK(I27)),"-",IFERROR(MAX(I27-$N$12,0),"-")) -> -
D28: =+MAX($D$14:D27)+1 -> 12 | E28: W&D: PCA/ESA/PLAN & COST CHECKLIST | F28: Open | I28: TBC | J28: Received. CC sent the materials needed. UHM must complete pipe work bbefore we close | N28: =IF(OR($F28="Closed",ISBLANK(I28)),"-",IFERROR(MAX(I28-$N$12,0),"-")) -> -
D29: Legal - Transaction | N29: =IF(OR($F29="Closed",ISBLANK(I29)),"-",IFERROR(MAX(I29-$N$12,0),"-")) -> -
D30: =+MAX($D$14:D29)+1 -> 13 | E30: Draft, review and execute PSA | F30: Closed | G30: PK | H30: Nixon | I30: 46101 | J30: Executed 3/20 | N30: =IF(OR($F30="Closed",ISBLANK(I30)),"-",IFERROR(MAX(I30-$N$12,0),"-")) -> -
D31: =+MAX($D$14:D30)+1 -> 14 | E31: Run down cost estimates for all Goodwin legal | F31: Closed | G31: PK | H31: Goodwin | I31: 46063 | J31: $2,900. To confirm on timing. Bank account is opened | N31: =IF(OR($F31="Closed",ISBLANK(I31)),"-",IFERROR(MAX(I31-$N$12,0),"-")) -> -
D32: =+MAX($D$14:D31)+1 -> 15 | E32: Confirm if Menkiti drafting GP JVA | F32: Closed | G32: PK | H32: MG | I32: 46068 | J32: MG drafting | N32: =IF(OR($F32="Closed",ISBLANK(I32)),"-",IFERROR(MAX(I32-$N$12,0),"-")) -> -
D33: =+MAX($D$14:D32)+1 -> 16 | E33: Confirm if Menkiti drafting LPA (Co-GPs and OCF) | F33: Closed | G33: PK | H33: MG | I33: 46014 | J33: MG drafting | N33: =IF(OR($F33="Closed",ISBLANK(I33)),"-",IFERROR(MAX(I33-$N$12,0),"-")) -> -
D34: =+MAX($D$14:D33)+1 -> 17 | E34: Set up JV OA: (CC, MG, OCF LP) | F34: Open | G34: PK | H34: MG, Goodwin | J34: Discussing with Seller | N34: =IF(OR($F34="Closed",ISBLANK(I34)),"-",IFERROR(MAX(I34-$N$12,0),"-")) -> - | P34: HUD needs draft. CC decide on date needed by
D35: =+MAX($D$14:D34)+1 -> 18 | E35: Set GP OA: (CC, MG) | F35: Open | G35: PK | H35: MG | J35: MG drafting. Awaiting first draft | N35: =IF(OR($F35="Closed",ISBLANK(I35)),"-",IFERROR(MAX(I35-$N$12,0),"-")) -> - | P35: HUD needs draft. CC decide on date needed by
D36: =+MAX($D$14:D35)+1 -> 19 | E36: Set up Caste OA: (CC Partners, Special Co-GP) | F36: Closed | G36: PK | H36: Goodwin | I36: 46143 | J36: Document has been finalized | M36: INTERNAL | N36: =IF(OR($F36="Closed",ISBLANK(I36)),"-",IFERROR(MAX(I36-$N$12,0),"-")) -> -
D37: =+MAX($D$14:D36)+1 -> 20 | E37: Set up RAP UP Partners LLC deal (CC Partners) | F37: Closed | G37: PK | I37: 46148 | J37: Register entity in DA. Bank needs OA, EIN, articles of incorp. DS to circulate final doc. PK to set up entity | M37: INTERNAL | N37: =IF(OR($F37="Closed",ISBLANK(I37)),"-",IFERROR(MAX(I37-$N$12,0),"-")) -> -
D38: =+MAX($D$14:D37)+1 -> 21 | E38: Escrow $50K Deposit at PSA execution | F38: Closed | G38: PK | H38: MG | I38: =WORKDAY($G$5,5) -> 46108 | N38: =IF(OR($F38="Closed",ISBLANK(I38)),"-",IFERROR(MAX(I38-$N$12,0),"-")) -> -
D39: =+MAX($D$14:D38)+1 -> 22 | E39: Escrow $150K Deposit at DD exit | F39: Closed | G39: PK | H39: MG | I39: =WORKDAY($G$7,5) -> 46168 | N39: =IF(OR($F39="Closed",ISBLANK(I39)),"-",IFERROR(MAX(I39-$N$12,0),"-")) -> -
D40: =+MAX($D$14:D39)+1 -> 23 | E40: Draft / Review PMA | F40: Closed | G40: DS | H40: Nixon/MG | J40: Finalizing remaining language. | N40: =IF(OR($F40="Closed",ISBLANK(I40)),"-",IFERROR(MAX(I40-$N$12,0),"-")) -> -
D41: =+MAX($D$14:D40)+1 -> 24 | E41: Release Murphy Consulting on HUD 2530 Clearance | F41: Open | H41: MG / Murphy | J41: In waiting mode. | N41: =IF(OR($F41="Closed",ISBLANK(I41)),"-",IFERROR(MAX(I41-$N$12,0),"-")) -> -
D42: =+MAX($D$14:D41)+1 -> 25 | E42: Confirm EOHLC's waiver | F42: Open | G42: PK | I42: 46178 | J42: Received 40T exemption letter on 7/13
D43: =+MAX($D$14:D42)+1 -> 26 | E43: Lender requires No more than 3 units vacant for 90 days before closing - send message to UHM | F43: Closed | G43: PK
D44: =+MAX($D$14:D43)+1 -> 27 | E44: Send Murphy Requested Information | F44: Closed | G44: AS | J44: Sent 3.18.26
D45: =+MAX($D$14:D44)+1 -> 28 | E45: Review list of deliverables for HUD 2530 Clearance | F45: Closed | H45: MG / Murphy | I45: TBC | J45: MG is running point. | N45: =IF(OR($F45="Closed",ISBLANK(I45)),"-",IFERROR(MAX(I45-$N$12,0),"-")) -> -
D46: =+MAX($D$14:D45)+1 -> 29 | E46: Send Walker & Dunlop PFS | F46: Closed | G46: AS | I46: 46100 | J46: CC/MG completed 3/20
D47: =+MAX($D$14:D46)+1 -> 30 | E47: Send Walker & Dunlop REO | F47: Closed | G47: AS | I47: 46100
D48: =+MAX($D$14:D47)+1 -> 31 | E48: Review Loan Docs | F48: Open | G48: PK | H48: Nixon | I48: TBC | J48: Call with MG Wed and Alex R on Friday morning | N48: =IF(OR($F48="Closed",ISBLANK(I48)),"-",IFERROR(MAX(I48-$N$12,0),"-")) -> -
D49: =+MAX($D$14:D48)+1 -> 32 | E49: Confirm Menkiti can fund Lender Deposit the week of close | F49: Open | G49: PK | H49: MG | I49: =+G11-5 -> 46278 | J49: Revert back in July
D50: =+MAX($D$14:D49)+1 -> 33 | E50: Engage with Seller to complete 40T process | F50: Closed | G50: PK | H50: Nixon | I50: 46145 | J50: Alex R (Nixon) working with confirm Ross (Seller) to submit. Ross has submitted | N50: =IF(OR($F50="Closed",ISBLANK(I50)),"-",IFERROR(MAX(I50-$N$12,0),"-")) -> -
D51: =+MAX($D$14:D50)+1 -> 34 | E51: HAP Application | F51: Open | G51: DS | H51: Nixon | I51: 46241 | J51: Still need to submit: Deed (DS working to follow up with Seller on updated language), Property Management Agreement (sending to Kelly today)
D52: =+MAX($D$14:D51)+1 -> 35 | E52: Draft Rollover Term Sheet (eg JV OA) | F52: Closed | G52: AS | H52: Nixon | I52: =+G7+45 -> 46206 | N52: =IF(OR($F52="Closed",ISBLANK(I52)),"-",IFERROR(MAX(I52-$N$12,0),"-")) -> -
D53: =+MAX($D$14:D52)+1 -> 36 | E53: Finalize pre-dev/deposit funding structure agreement | F53: Closed | H53: MG | I53: =+I38 -> 46108 | J53: PSA executed. Caste to send ASAP | N53: =IF(OR($F53="Closed",ISBLANK(I53)),"-",IFERROR(MAX(I53-$N$12,0),"-")) -> -
D54: =+MAX($D$14:D53)+1 -> 37 | E54: Review existing HAP Contract and prepare Assumption | F54: Closed | G54: PK | H54: Nixon, Jacques | I54: 46118 | J54: Ask Nixon for copy of HAP contract and exhibits | N54: =IF(OR($F54="Closed",ISBLANK(I54)),"-",IFERROR(MAX(I54-$N$12,0),"-")) -> -
D55: =+MAX($D$14:D54)+1 -> 38 | E55: Send Darryl finalized DD External list (within 3 days of LOI execution) | F55: Closed | G55: AS | N55: =IF(OR($F55="Closed",ISBLANK(I55)),"-",IFERROR(MAX(I55-$N$12,0),"-")) -> -
D56: Physical DD + CapEx Plan | N56: =IF(OR($F56="Closed",ISBLANK(I56)),"-",IFERROR(MAX(I56-$N$12,0),"-")) -> -
D57: =+MAX($D$14:D56)+1 -> 39 | E57: ='Internal - DD Request List'!E44 -> Engage Property Inspection Firm for full property review | F57: Closed | N57: =IF(OR($F57="Closed",ISBLANK(I57)),"-",IFERROR(MAX(I57-$N$12,0),"-")) -> -
D58: =+MAX($D$14:D57)+1 -> 40 | E58: ='Internal - DD Request List'!E45 -> Physical Reports / Property Condition Reports | F58: Closed | G58: DS | I58: =+G7 -> 46161 | J58: EBI released on 3/20. EBI will use drones to review roof due to inability to safely access roof during DD. | N58: =IF(OR($F58="Closed",ISBLANK(I58)),"-",IFERROR(MAX(I58-$N$12,0),"-")) -> -
D59: =+MAX($D$14:D58)+1 -> 41 | E59: Confirm HUD reqs with Nixon/Lenders (e.g. need PCR or CNA?) | F59: Closed | G59: DS/AS | I59: 46052 | J59: Need both PCR and HUD blessed CNA | N59: =IF(OR($F59="Closed",ISBLANK(I59)),"-",IFERROR(MAX(I59-$N$12,0),"-")) -> -
D60: =+MAX($D$14:D59)+1 -> 42 | E60: ='Internal - DD Request List'!E46 -> Roof Reports/Repairs/Maintenance | F60: Closed | G60: DS | I60: 46096 | J60: there is an existing roof report (Feb '25) | N60: =IF(OR($F60="Closed",ISBLANK(I60)),"-",IFERROR(MAX(I60-$N$12,0),"-")) -> -
D61: =+MAX($D$14:D60)+1 -> 43 | E61: ='Internal - DD Request List'!E47 -> Structural & Seismic Reports | F61: Closed | G61: DS | I61: 46096 | J61: Not typically required by lender. No existing reports available | N61: =IF(OR($F61="Closed",ISBLANK(I61)),"-",IFERROR(MAX(I61-$N$12,0),"-")) -> -
D62: =+MAX($D$14:D61)+1 -> 44 | E62: ='Internal - DD Request List'!E48 -> Work Orders/PM Logs (HVAC, R&M, Roof, etc.) | F62: Closed | G62: PK | I62: 46096 | J62: ='Internal - DD Request List'!K48 -> Rec'd Detailed Worklog 1/1-1/12, Summary 2025. UHM is working with IT to get detailed log for 2025. | N62: =IF(OR($F62="Closed",ISBLANK(I62)),"-",IFERROR(MAX(I62-$N$12,0),"-")) -> -
D63: =+MAX($D$14:D62)+1 -> 45 | E63: ='Internal - DD Request List'!E51 -> Service Agreements (list) | F63: Closed | G63: DS | I63: 46096 | J63: ='Internal - DD Request List'!K51 -> Received: pest control, snow removal and janitorial. No others | N63: =IF(OR($F63="Closed",ISBLANK(I63)),"-",IFERROR(MAX(I63-$N$12,0),"-")) -> -
D64: =+MAX($D$14:D63)+1 -> 46 | E64: ='Internal - DD Request List'!E52 -> Warranties (list) | F64: Closed | G64: DS | I64: 46096 | J64: ='Internal - DD Request List'!K52 -> Seller: N/A | N64: =IF(OR($F64="Closed",ISBLANK(I64)),"-",IFERROR(MAX(I64-$N$12,0),"-")) -> -
D65: =+MAX($D$14:D64)+1 -> 47 | E65: ='Internal - DD Request List'!E53 -> Vendor Contact List | F65: Closed | G65: DS | I65: 46096 | N65: =IF(OR($F65="Closed",ISBLANK(I65)),"-",IFERROR(MAX(I65-$N$12,0),"-")) -> - | V65: 46204
D66: =+MAX($D$14:D65)+1 -> 48 | E66: ='Internal - DD Request List'!E54 -> Utility Account Numbers List & Identification | F66: Closed | G66: PK | I66: 46096 | J66: Under acct # for all props and ensure they're active/any open payables | N66: =IF(OR($F66="Closed",ISBLANK(I66)),"-",IFERROR(MAX(I66-$N$12,0),"-")) -> -
D67: =+MAX($D$14:D66)+1 -> 49 | E67: ='Internal - DD Request List'!E55 -> Utility Allowance Schedule | F67: Closed | G67: DS | I67: 46096 | N67: =IF(OR($F67="Closed",ISBLANK(I67)),"-",IFERROR(MAX(I67-$N$12,0),"-")) -> -
D68: =+MAX($D$14:D67)+1 -> 50 | E68: ='Internal - DD Request List'!E56 -> Special Claims History | F68: Closed | G68: DS | I68: 46096 | J68: ='Internal - DD Request List'!K56 -> Seller: N/A | N68: =IF(OR($F68="Closed",ISBLANK(I68)),"-",IFERROR(MAX(I68-$N$12,0),"-")) -> -
D69: =+MAX($D$14:D68)+1 -> 51 | E69: ='Internal - DD Request List'!E57 -> Repayment Agreements (if any) | F69: Closed | G69: DS | I69: 46096 | J69: ='Internal - DD Request List'!K57 -> Seller: N/A | N69: =IF(OR($F69="Closed",ISBLANK(I69)),"-",IFERROR(MAX(I69-$N$12,0),"-")) -> -
D70: =+MAX($D$14:D69)+1 -> 52 | E70: ='Internal - DD Request List'!E58 -> VAWA Transfer Log (if applicable) | F70: Closed | G70: DS | I70: 46096 | J70: ='Internal - DD Request List'!K58 -> Seller: N/A | N70: =IF(OR($F70="Closed",ISBLANK(I70)),"-",IFERROR(MAX(I70-$N$12,0),"-")) -> -
D71: =+MAX($D$14:D70)+1 -> 53 | E71: ='Internal - DD Request List'!E59 -> Reasonable Accomodation Request Log (if applicable) | F71: Closed | G71: DS | I71: 46096 | J71: ='Internal - DD Request List'!K59 -> Seller: N/A | N71: =IF(OR($F71="Closed",ISBLANK(I71)),"-",IFERROR(MAX(I71-$N$12,0),"-")) -> -
D72: =+MAX($D$14:D71)+1 -> 54 | E72: ='Internal - DD Request List'!E60 -> Fire Escape (5 year certs) | F72: Closed | G72: DS | I72: 46096 | J72: ='Internal - DD Request List'!K60 -> Seller: N/A | N72: =IF(OR($F72="Closed",ISBLANK(I72)),"-",IFERROR(MAX(I72-$N$12,0),"-")) -> -
D73: =+MAX($D$14:D72)+1 -> 55 | E73: ='Internal - DD Request List'!E61 -> HVAC Unit Inventory and Description | F73: Closed | G73: DS | I73: 46096 | J73: ='Internal - DD Request List'!K61 -> Seller: N/A | N73: =IF(OR($F73="Closed",ISBLANK(I73)),"-",IFERROR(MAX(I73-$N$12,0),"-")) -> -
D74: =+MAX($D$14:D73)+1 -> 56 | E74: ='Internal - DD Request List'!E62 -> Infra-red/Thermographic Scan | F74: Closed | G74: DS | I74: 46096 | J74: ='Internal - DD Request List'!K62 -> Seller: N/A | N74: =IF(OR($F74="Closed",ISBLANK(I74)),"-",IFERROR(MAX(I74-$N$12,0),"-")) -> -
D75: =+MAX($D$14:D74)+1 -> 57 | E75: Review draft CAPEX budget - Base Building and Units | F75: Closed | G75: DS | I75: =+G7 -> 46161 | J75: UHM to provide responses to CC/MG follow up questions on CAPEX/OPEX | N75: =IF(OR($F75="Closed",ISBLANK(I75)),"-",IFERROR(MAX(I75-$N$12,0),"-")) -> -
D76: =+MAX($D$14:D75)+1 -> 58 | E76: Prepare questions, recommendations for CC to discuss with APR | F76: Closed | G76: BA | H76: Jacques | I76: 46096 | N76: =IF(OR($F76="Closed",ISBLANK(I76)),"-",IFERROR(MAX(I76-$N$12,0),"-")) -> -
D77: =+MAX($D$14:D76)+1 -> 59 | E77: Let Seller know we need to be on all RCS communications | F77: Closed | G77: AS | I77: 46014 | N77: =IF(OR($F77="Closed",ISBLANK(I77)),"-",IFERROR(MAX(I77-$N$12,0),"-")) -> -
D78: =+MAX($D$14:D77)+1 -> 60 | E78: Tour portfolio and review draft Rent Comp Study w/ APR | F78: Closed | G78: BA | I78: 46060 | J78: Toured on 1/15 w/ Frank Molis (APR). | N78: =IF(OR($F78="Closed",ISBLANK(I78)),"-",IFERROR(MAX(I78-$N$12,0),"-")) -> -
D79: =+MAX($D$14:D78)+1 -> 61 | E79: Pay APR for the RCS | F79: Closed | G79: AS/BA | N79: =IF(OR($F79="Closed",ISBLANK(I79)),"-",IFERROR(MAX(I79-$N$12,0),"-")) -> -
D80: =+MAX($D$14:D79)+1 -> 62 | E80: ='Internal - DD Request List'!E11 -> Title and Zoning review | F80: Open | N80: =IF(OR($F80="Closed",ISBLANK(I80)),"-",IFERROR(MAX(I80-$N$12,0),"-")) -> -
D81: =+MAX($D$14:D80)+1 -> 63 | E81: ='Internal - DD Request List'!E12 -> ALTA Survey | F81: Open | G81: DS | I81: =+G7 -> 46161 | J81: Draft is FINAL until signed before closing. | N81: =IF(OR($F81="Closed",ISBLANK(I81)),"-",IFERROR(MAX(I81-$N$12,0),"-")) -> 0
D82: =+MAX($D$14:D81)+1 -> 64 | E82: ='Internal - DD Request List'!E13 -> Title Commitment | F82: Closed | G82: DS | I82: 46188 | J82: DONE | N82: =IF(OR($F82="Closed",ISBLANK(I82)),"-",IFERROR(MAX(I82-$N$12,0),"-")) -> -
D83: =+MAX($D$14:D82)+1 -> 65 | E83: Lot L Tax Issue | F83: Open | G83: DS | I83: 46266 | J83: Redemption of tax taking to be recorded by Seller prior to closing.
D84: =+MAX($D$14:D83)+1 -> 66 | E84: Zoning certification | F84: Closed | G84: DS | I84: 46096 | J84: Lender requires zoning cert. Sam at Nixon is getting ($400/property) | N84: =IF(OR($F84="Closed",ISBLANK(I84)),"-",IFERROR(MAX(I84-$N$12,0),"-")) -> -
D85: =+MAX($D$14:D84)+1 -> 67 | E85: ='Internal - DD Request List'!E15 -> All City/State permits | F85: Closed | G85: DS | I85: 46096 | J85: ='Internal - DD Request List'!K15 -> Seller: N/A | N85: =IF(OR($F85="Closed",ISBLANK(I85)),"-",IFERROR(MAX(I85-$N$12,0),"-")) -> -
D86: =+MAX($D$14:D85)+1 -> 68 | E86: ='Internal - DD Request List'!E16 -> Easement Documents (if applicable) | F86: Closed | G86: DS | I86: 46096 | J86: ='Internal - DD Request List'!K16 -> Seller: N/A | N86: =IF(OR($F86="Closed",ISBLANK(I86)),"-",IFERROR(MAX(I86-$N$12,0),"-")) -> -
D87: =+MAX($D$14:D86)+1 -> 69 | E87: ='Internal - DD Request List'!E17 -> Confirm FEMA Flood Vulnerable Status | F87: Closed | G87: DS | I87: 46096 | J87: Feldman will confirm as part of ALTA work. Not a req from Northmarq | N87: =IF(OR($F87="Closed",ISBLANK(I87)),"-",IFERROR(MAX(I87-$N$12,0),"-")) -> -
D88: =+MAX($D$14:D87)+1 -> 70 | E88: ='Internal - DD Request List'!E18 -> Permits Required for Property Operation (e.g. flammable fuel storage) | F88: Closed | G88: DS | I88: 46096 | J88: ='Internal - DD Request List'!K18 -> Seller: N/A | N88: =IF(OR($F88="Closed",ISBLANK(I88)),"-",IFERROR(MAX(I88-$N$12,0),"-")) -> -
D89: =+MAX($D$14:D88)+1 -> 71 | E89: ='Internal - DD Request List'!E19 -> Environmental Information review | F89: Closed | N89: =IF(OR($F89="Closed",ISBLANK(I89)),"-",IFERROR(MAX(I89-$N$12,0),"-")) -> -
D90: =+MAX($D$14:D89)+1 -> 72 | E90: ='Internal - DD Request List'!E20 -> Phase 1 ESA | F90: Closed | G90: DS | I90: 46096 | J90: EBI released 3/20. Finalized | N90: =IF(OR($F90="Closed",ISBLANK(I90)),"-",IFERROR(MAX(I90-$N$12,0),"-")) -> -
D91: =+MAX($D$14:D90)+1 -> 73 | E91: ='Internal - DD Request List'!E21 -> Hazardous Materials report | F91: Closed | G91: DS | I91: 46096 | J91: ='Internal - DD Request List'!K21 -> Seller: N/A | N91: =IF(OR($F91="Closed",ISBLANK(I91)),"-",IFERROR(MAX(I91-$N$12,0),"-")) -> -
D92: =+MAX($D$14:D91)+1 -> 74 | E92: ='Internal - DD Request List'!E22 -> Geotechnical soils report | F92: Closed | G92: DS | I92: 46096 | J92: ='Internal - DD Request List'!K22 -> Seller: N/A | N92: =IF(OR($F92="Closed",ISBLANK(I92)),"-",IFERROR(MAX(I92-$N$12,0),"-")) -> -
D93: =+MAX($D$14:D92)+1 -> 75 | E93: ='Internal - DD Request List'!E23 -> Lead abatement/compliance report | F93: Closed | G93: DS | I93: 46096 | J93: ='Internal - DD Request List'!K23 -> Letter of Full Deleading Compliance, 11/17/1998 | N93: =IF(OR($F93="Closed",ISBLANK(I93)),"-",IFERROR(MAX(I93-$N$12,0),"-")) -> -
D94: =+MAX($D$14:D93)+1 -> 76 | E94: ='Internal - DD Request List'!E24 -> Mold reports/remediation | F94: Closed | G94: DS | I94: 46096 | J94: ='Internal - DD Request List'!K24 -> Seller: N/A | N94: =IF(OR($F94="Closed",ISBLANK(I94)),"-",IFERROR(MAX(I94-$N$12,0),"-")) -> -
D95: =+MAX($D$14:D94)+1 -> 77 | E95: ='Internal - DD Request List'!E25 -> Indoor air quality reports | F95: Closed | G95: DS | I95: 46096 | J95: ='Internal - DD Request List'!K25 -> Seller: N/A | N95: =IF(OR($F95="Closed",ISBLANK(I95)),"-",IFERROR(MAX(I95-$N$12,0),"-")) -> -
D96: =+MAX($D$14:D95)+1 -> 78 | E96: ='Internal - DD Request List'!E26 -> Water intrusion/moisture issues | F96: Closed | G96: DS | I96: 46096 | J96: ='Internal - DD Request List'!K26 -> Seller: N/A | N96: =IF(OR($F96="Closed",ISBLANK(I96)),"-",IFERROR(MAX(I96-$N$12,0),"-")) -> -
D97: =+MAX($D$14:D96)+1 -> 79 | E97: ='Internal - DD Request List'!E29 -> Request Drawings + confirm building Specs | F97: Closed | G97: DS | N97: =IF(OR($F97="Closed",ISBLANK(I97)),"-",IFERROR(MAX(I97-$N$12,0),"-")) -> -
D98: =+MAX($D$14:D97)+1 -> 80 | E98: ='Internal - DD Request List'!E30 -> Site Plans/Building Plans / Construction Plans / As-Builts | F98: Closed | G98: DS | I98: 46096 | J98: ='Internal - DD Request List'!K30 -> Seller: N/A | N98: =IF(OR($F98="Closed",ISBLANK(I98)),"-",IFERROR(MAX(I98-$N$12,0),"-")) -> -
D99: =+MAX($D$14:D98)+1 -> 81 | E99: ='Internal - DD Request List'!E31 -> Building Permits | F99: Closed | G99: DS | I99: 46096 | J99: ='Internal - DD Request List'!K31 -> Seller: N/A | N99: =IF(OR($F99="Closed",ISBLANK(I99)),"-",IFERROR(MAX(I99-$N$12,0),"-")) -> -
D100: =+MAX($D$14:D99)+1 -> 82 | E100: ='Internal - DD Request List'!E32 -> Certificates of Occupancy | F100: Closed | G100: DS | I100: 46096 | J100: ='Internal - DD Request List'!K32 -> Received all but one. 63 Lambert does not exist. See Zoning Cert from Title Company's attorney. CC to decide whether to clean up post-closing | N100: =IF(OR($F100="Closed",ISBLANK(I100)),"-",IFERROR(MAX(I100-$N$12,0),"-")) -> -
D101: =+MAX($D$14:D100)+1 -> 83 | E101: ='Internal - DD Request List'!E33 -> Building areas - Building GSF, Unit RSF's | F101: Closed | G101: DS | I101: 46096 | J101: ='Internal - DD Request List'!K33 -> Seller: N/A | N101: =IF(OR($F101="Closed",ISBLANK(I101)),"-",IFERROR(MAX(I101-$N$12,0),"-")) -> -
D102: =+MAX($D$14:D101)+1 -> 84 | E102: ='Internal - DD Request List'!E35 -> REAC reports and scores from prior 3 years | F102: Closed | G102: CC | I102: 46096 | J102: ='Internal - DD Request List'!K35 -> Rec'd 2025, Seller: Only one score from past 5 years | N102: =IF(OR($F102="Closed",ISBLANK(I102)),"-",IFERROR(MAX(I102-$N$12,0),"-")) -> -
...

Sheet Internal - DD Request List
D2: DUE DILIGENCE REQUEST LIST | F2: UPDATED AS OF:
D3: RAP UP Portfolio | F3: 46035
I4: =+TODAY() -> 46217
C5: DIV Folder | D5: Item # | E5: Document | F5: Status | G5: Department | H5: Responsible Party | I5: DIV Comment | J5: Partner Comment | K5: Notes
D6: LEASING & MARKETING
D7: =+MAX($D$5:D5)+1 -> 1 | E7: Review Residential Leases & House Rules | F7: Open | G7: Leasing / Marketing | K7: Rec'd House Rules, Form Lease, need all leases, LEASES ON SITE NEED TO REVIEW
D8: =+MAX($D$5:D7)+1 -> 2 | E8: Review License Agreements (if applicable) | F8: Closed | G8: Leasing / Marketing | K8: Seller: N/A
D9: =+MAX($D$5:D8)+1 -> 3 | E9: Review Indemnities (if applicable) | F9: Closed | G9: Leasing / Marketing | K9: Seller: N/A
D10: PHYSICAL / PROPERTY
E11: Title and Zoning review | G11: Development
D12: =+MAX($D$5:D11)+1 -> 4 | E12: ALTA Survey | F12: Closed | G12: Development | K12: Seller: N/A
D13: =+MAX($D$5:D12)+1 -> 5 | E13: Title Commitment | F13: Open | G13: Development | K13: Owners & Lender Policy
D14: =+MAX($D$5:D13)+1 -> 6 | E14: Deleted | F14: Deleted | G14: Deleted
D15: =+MAX($D$5:D14)+1 -> 7 | E15: All City/State permits | F15: Closed | G15: Development | K15: Seller: N/A
D16: =+MAX($D$5:D15)+1 -> 8 | E16: Easement Documents (if applicable) | F16: Closed | G16: Development | K16: Seller: N/A
D17: =+MAX($D$5:D16)+1 -> 9 | E17: Confirm FEMA Flood Vulnerable Status | F17: Closed | G17: Development | K17: Seller: N/A
D18: =+MAX($D$5:D17)+1 -> 10 | E18: Permits Required for Property Operation (e.g. flammable fuel storage) | F18: Closed | G18: Development | K18: Seller: N/A
E19: Environmental Information review
D20: =+MAX($D$5:D19)+1 -> 11 | E20: Phase 1 ESA | F20: Closed | G20: Development | K20: Seller: N/A
D21: =+MAX($D$5:D20)+1 -> 12 | E21: Hazardous Materials report | F21: Closed | G21: Development | K21: Seller: N/A
D22: =+MAX($D$5:D21)+1 -> 13 | E22: Geotechnical soils report | F22: Closed | G22: Development | K22: Seller: N/A
D23: =+MAX($D$5:D22)+1 -> 14 | E23: Lead abatement/compliance report | F23: Received | G23: Development | K23: Letter of Full Deleading Compliance, 11/17/1998
D24: =+MAX($D$5:D23)+1 -> 15 | E24: Mold reports/remediation | F24: Closed | G24: Development | K24: Seller: N/A
D25: =+MAX($D$5:D24)+1 -> 16 | E25: Indoor air quality reports | F25: Closed | G25: Development | K25: Seller: N/A
D26: =+MAX($D$5:D25)+1 -> 17 | E26: Water intrusion/moisture issues | F26: Closed | G26: Development | K26: Seller: N/A
D27: =+MAX($D$5:D26)+1 -> 18 | E27: Deleted | F27: Deleted | G27: Deleted
D28: =+MAX($D$5:D27)+1 -> 19 | E28: Deleted | F28: Deleted | G28: Deleted
E29: Request Drawings + confirm building Specs
D30: =+MAX($D$5:D29)+1 -> 20 | E30: Site Plans/Building Plans / Construction Plans / As-Builts | F30: Closed | G30: Development | K30: Seller: N/A
D31: =+MAX($D$5:D30)+1 -> 21 | E31: Building Permits | F31: Closed | G31: Development | K31: Seller: N/A
D32: =+MAX($D$5:D31)+1 -> 22 | E32: Certificates of Occupancy | F32: Received | G32: Development | K32: Received all but one. 63 Lambert does not exist. See Zoning Cert from Title Company's attorney. CC to decide whether to clean up post-closing
D33: =+MAX($D$5:D32)+1 -> 23 | E33: Building areas - Building GSF, Unit RSF's | F33: Closed | G33: Development | K33: Seller: N/A
D34: =+MAX($D$5:D33)+1 -> 24 | E34: Deleted | F34: Deleted | G34: Deleted
D35: =+MAX($D$5:D34)+1 -> 25 | E35: REAC reports and scores from prior 3 years | F35: Closed | G35: Development | K35: Rec'd 2025, Seller: Only one score from past 5 years
D36: =+MAX($D$5:D35)+1 -> 26 | E36: Capital Needs Assessment | F36: Closed | G36: Development | K36: 2021, Seller: CNA good for 10 years
D37: =+MAX($D$5:D36)+1 -> 27 | E37: Keith Construction budget | F37: Open
D38: PROPERTY MANAGEMENT
E39: Schedule calls with UHM to review (DD materials, budget). Walk property with onsite team
D40: =+MAX($D$5:D39)+1 -> 28 | E40: 2026 Operating Budget | F40: Received | G40: Prop Mgmt
D41: =+MAX($D$5:D40)+1 -> 29 | E41: Management & Occupancy Review past 3 years | F41: Open | K41: Received 2023 and 2025; No 2024 report exists
D42: =+MAX($D$5:D41)+1 -> 30 | E42: Personal Property Inventory | F42: Closed | G42: Prop Mgmt | K42: Seller: N/A
D43: =+MAX($D$5:D42)+1 -> 31 | E43: Photographs | F43: Received | G43: Prop Mgmt
E44: Engage Property Inspection Firm for full property review
D45: =+MAX($D$5:D43)+1 -> 32 | E45: Physical Reports / Property Condition Reports | F45: Closed | G45: Prop Mgmt | K45: Seller: N/A
D46: =+MAX($D$5:D45)+1 -> 33 | E46: Roof Reports/Repairs/Maintenance | F46: Open | G46: Prop Mgmt | K46: Feb 2025 inspection reports for all roofs. No R&M info. Seller: Requested
D47: =+MAX($D$5:D46)+1 -> 34 | E47: Structural & Seismic Reports | F47: Closed | G47: Prop Mgmt | K47: Seller: N/A
D48: =+MAX($D$5:D47)+1 -> 35 | E48: Work Orders/PM Logs (HVAC, R&M, Roof, etc.) | F48: Open | G48: Prop Mgmt | K48: Rec'd Detailed Worklog 1/1-1/12, Summary 2025. UHM is working with IT to get detailed log for 2025.
D49: =+MAX($D$5:D48)+1 -> 36 | E49: Deleted | F49: Deleted | G49: Deleted
D50: =+MAX($D$5:D49)+1 -> 37 | E50: Deleted | F50: Deleted | G50: Deleted
D51: =+MAX($D$5:D50)+1 -> 38 | E51: Service Agreements (list) | F51: Received | G51: Prop Mgmt | K51: Received: pest control, snow removal and janitorial. No others
D52: =+MAX($D$5:D51)+1 -> 39 | E52: Warranties (list) | F52: Closed | G52: Prop Mgmt | K52: Seller: N/A
D53: =+MAX($D$5:D52)+1 -> 40 | E53: Vendor Contact List | F53: Received | G53: Prop Mgmt
D54: =+MAX($D$5:D53)+1 -> 41 | E54: Utility Account Numbers List & Identification | F54: Received | G54: Prop Mgmt
D55: =+MAX($D$5:D54)+1 -> 42 | E55: Utility Allowance Schedule | F55: Received | G55: Prop Mgmt
D56: =+MAX($D$5:D55)+1 -> 43 | E56: Special Claims History | F56: Closed | G56: Prop Mgmt | K56: Seller: N/A
D57: =+MAX($D$5:D56)+1 -> 44 | E57: Repayment Agreements (if any) | F57: Closed | G57: Prop Mgmt | K57: Seller: N/A
D58: =+MAX($D$5:D57)+1 -> 45 | E58: VAWA Transfer Log (if applicable) | F58: Closed | G58: Prop Mgmt | K58: Seller: N/A
D59: =+MAX($D$5:D58)+1 -> 46 | E59: Reasonable Accomodation Request Log (if applicable) | F59: Closed | G59: Prop Mgmt | K59: Seller: N/A
D60: =+MAX($D$5:D59)+1 -> 47 | E60: Fire Escape (5 year certs) | F60: Closed | G60: Prop Mgmt | K60: Seller: N/A
D61: =+MAX($D$5:D60)+1 -> 48 | E61: HVAC Unit Inventory and Description | F61: Closed | G61: Prop Mgmt | K61: Seller: N/A
D62: =+MAX($D$5:D61)+1 -> 49 | E62: Infra-red/Thermographic Scan | F62: Closed | G62: Prop Mgmt | K62: Seller: N/A
D63: =+MAX($D$5:D62)+1 -> 50 | E63: Deleted | F63: Deleted | G63: Deleted
D64: AFFORDABLE
E65: Review UHM's in-place management process
D66: =+MAX($D$5:D63)+1 -> 51 | E66: Sample 50059 files including one current resident with recertification and one former tenant | F66: Received | G66: Prop Mgmt
D67: =+MAX($D$5:D66)+1 -> 52 | E67: Original HAP Contract | F67: Received | G67: Prop Mgmt
D68: =+MAX($D$5:D67)+1 -> 53 | E68: HAP Billing Files (HUD 52670A) - YTD and prior year | F68: Received
D69: =+MAX($D$5:D68)+1 -> 54 | E69: Tenant Selection Plan | F69: Received | G69: Prop Mgmt
D70: =+MAX($D$5:D69)+1 -> 55 | E70: Affirmative Fair Housing Marketing Plan | F70: Received | G70: Prop Mgmt | K70: Document says existing plan expired 1/31/2021. Latest plan per UHM
D71: =+MAX($D$5:D70)+1 -> 56 | E71: Enterprise Income Verification (EIV) Master File | F71: Open | K71: Requires HUD approval, need update from UHM
D72: =+MAX($D$5:D71)+1 -> 57 | E72: Extended Use Agreement (if applicable) | F72: Closed | G72: Prop Mgmt | K72: Seller: N/A
D73: =+MAX($D$5:D72)+1 -> 58 | E73: Current Waitlist | F73: Received | G73: Prop Mgmt | K73: Dated 1/6/26
D74: =+MAX($D$5:D73)+1 -> 59 | E74: Recent Management and Occupancy Review (MOR) reports from last 3 years | F74: Received | G74: Prop Mgmt | K74: Date of report is 8/18/25 but document says expiration 4/30/2018? Please confirm there were no other MORs completed under current ownership. And confirm the difference between this document and (29) MOR. This is a typo - these reports don't expire; The report in this folder should be with the other MOR reports
D75: =+MAX($D$5:D74)+1 -> 60 | E75: Any non-compliance agency or audit findings from last 3 years | F75: Closed | G75: Prop Mgmt | K75: Seller: N/A
D76: =+MAX($D$5:D75)+1 -> 61 | E76: Most recent RCS & any relevant information provided; General update to progress of new RCS | F76: Received | K76: In progress, Contract with CC.
D77: LEGAL, INSURANCE AND TAX DOCUMENTS
E78: Review of Property Tax, Legal, Insurance docs
D79: =+MAX($D$5:D78)+1 -> 62 | E79: Insurance Policies/Summary Docs/Exclusions | F79: Received | G79: Legal/Ins/Tax | K79: GNY GL, Excess Policy from GNY & AXIS. Expires 10/2026, Travelers Property Insurance
D80: =+MAX($D$5:D79)+1 -> 63 | E80: Summary of Litigation Pending or in Progress | F80: Received | G80: Legal/Ins/Tax | K80: 5 tenants pending litigation
D81: =+MAX($D$5:D80)+1 -> 64 | E81: Summary of Outstanding Insurance Claims | F81: Received | G81: Legal/Ins/Tax | K81: None
D82: =+MAX($D$5:D81)+1 -> 65 | E82: Tax Appeals / Reduction History | F82: Open | G82: Legal/Ins/Tax
D83: =+MAX($D$5:D82)+1 -> 66 | E83: Tax Bills YTD + 3 prior years (including unsecured personal property) | F83: Open | G83: Legal/Ins/Tax | K83: 2025: Only Q2 and Q3 provided? 2024: Only Q1 and Q3 provided? 2023: Only Q3 provided? 2022: Only Q4 provided?
D84: =+MAX($D$5:D83)+1 -> 67 | E84: Total Insured Value (TIV) / Claims and Loss History - prior 3 years | F84: Received | G84: Legal/Ins/Tax
D85: =+MAX($D$5:D84)+1 -> 68 | E85: Property Management Agreement | F85: Received | G85: Legal/Ins/Tax
D86: ACCOUNTING / FINANCE
E87: Review Historical Financials (Accounting/Finance)
D88: =+MAX($D$5:D86)+1 -> 69 | E88: Aged Receivable / Delinquency Report YTD (update if available) + 3 prior years | F88: Received | G88: Accounting | K88: 2023,2024, 2025, YTD thru 1/5
D89: =+MAX($D$5:D88)+1 -> 70 | E89: Appraisals | F89: Received | G89: Accounting
D90: =+MAX($D$5:D89)+1 -> 71 | E90: Detailed Operating Budget YTD + 3 prior years | F90: Received | G90: Accounting
D91: =+MAX($D$5:D90)+1 -> 72 | E91: Capital Expenditures - Historical (3 prior years) & 2026 Budget | F91: Open | G91: Accounting
D92: =+MAX($D$5:D91)+1 -> 73 | E92: Deferred Maintenance | F92: Open | G92: Accounting
D93: =+MAX($D$5:D92)+1 -> 74 | E93: Rent Statements YTD + 3 prior years | F93: Received | G93: Accounting | K93: 2023, 2024, 2025
D94: =+MAX($D$5:D93)+1 -> 75 | E94: Security Deposits Schedule | F94: Open | G94: Accounting
D95: =+MAX($D$5:D94)+1 -> 76 | E95: Tenant Billing Register YTD + 3 prior years | F95: Received | G95: Accounting
D96: =+MAX($D$5:D95)+1 -> 77 | E96: Utility Bills - 12 months | F96: Received | G96: Accounting
D97: =+MAX($D$5:D96)+1 -> 78 | E97: Vendor Bills - 3 prior years | F97: Received | G97: Accounting
J65506: still need

Sheet HAP Assignment Checklist
A2: HAP Assignment Checklist (with HUD Exhibit 2 items)
A3: General Information
A4: Name: | D4: How does 2530 HUD Clearance layer into this? | F4: Seller:
A5: Address: | D5: Any docs we need to get Darryl now? | F5: FHA:
A6: Contract: | F6: PBCA:
A7: New Owner: | F7: HUD AE:
A8: Section 1 | C8: Proposed Owner Information | D8: Responsible Party | E8: CC/MG Notes | F8: Status | G8: Comments
B9: a. | C9: Name and signature block for Proposed Owner entity | D9: John Daniels | G9: Borrower Name:
B10: b. | C10: Organizational Chart for Proposed Owner entity (with percentage interests and roles for all entities and individuals) | D10: Caste - Nixon
B11: c. | C11: Resume for Proposed Owner or sponsor (include any affordable experience) | D11: John Daniels | E11: Will this be both CC and MG?
B12: d. | C12: Articles of Organization/Certificate of Formation/Certificate of Limited Partnership | D12: John Daniels | G12: State of Formation:
B13: e. | C13: Operating Agreement/Limited Partnership Agreement | D13: John Daniels | G13: Date of Operating Agreement:
B14: f. | C14: 2530 Previous Participation submission confirmation in APPS | D14: John Daniels | G14: APPS Submission Number: Confirm entities are registered in Business Partner Registration if paper 2530 is submitted in lieu of APPS submission.
B15: g. | C15: Real Estate Owned (REO) Schedule | D15: John Daniels | E15: Will this be both CC and MG? Trace control
B16: h. | C16: Purchaser's Financial Statement (HUD Form 92417) | D16: John Daniels | E16: Will this be both CC and MG? Trace control
B17: i. | C17: Unique Entity ID Registration Confirmation | D17: John Daniels | E17: Will this be both CC and MG? Trace control | G17: Unique Entity ID:
B18: j. | C18: EIN Number for Proposed Owner entity | D18: John Daniels | E18: Will this be both CC and MG? Trace control | G18: EIN Number:
B19: k. | C19: Confirmation of Fiscal Year End Date | D19: John Daniels | E19: Will this be both CC and MG? Trace control
B20: l. | C20: Certificate of Good Standing | D20: John Daniels | E20: Will this be both CC and MG? Trace control
B21: m. | C21: Authorizing Resolution | D21: John Daniels | E21: Will this be both CC and MG? Trace control
B22: n. | C22: Credit Report for sponsor | D22: John Daniels | E22: Will this be both CC and MG? Trace control
A24: Section 2 | C24: Management Company Information
B25: a. | C25: Resume of Management Company | D25: Caste | E25: From UHM | G25: Name of Management Agent:
B26: b. | C26: Management Agent Certification (HUD Form 9839-B) | D26: N/A | E26: N/A with UHM staying in place?
C27: If new management is being retained at closing:
B28: c. | C28: Management Entity Profile (HUD Form 9832) | D28: Caste | E28: From UHM
B29: d. | C29: 2530 Previous Participation submission confirmation on APPS | D29: Caste | E29: From UHM | G29: APPS Submission Number: Confirm entities are registered in Business Partner Registration if paper 2530 is submitted in lieu of APPS submission.
B30: e. | C30: Proposed Tenant Selection Plan | D30: Caste | E30: From UHM
B31: f. | C31: Proposed Tenant Lease | D31: Caste | E31: From UHM | G31: Need confirmation that the agent will use the HUD form model lease (form HUD-90105a)
B32: g. | C32: Management Agreement with HUD required provisions | D32: Caste | E32: Can we use current or needs to be assigned?
A34: Section 3 | C34: Project Finances and Affordability
B35: a. | C35: Description of financing (LIHTC? Conventional? FHA? Tax-exempt bonds?) | D35: Caste | E35: Will likely be TBD prior to submission. Ok to follow
B36: b. | C36: Pro Forma Net Operating Income | D36: Caste
B37: c. | C37: Pro Forma Sources and Uses | D37: Caste
B38: d. | C38: Estimated closing date | D38: Caste | G38: Closing Date:
B39: e. | C39: Purchase and Sale Agreement and any amendments or assignments | D39: Caste | G39: Executed Date:
B40: f. | C40: Name and address of Lender | D40: Caste | G40: Lender Name:
B41: g. | C41: Name and address of Title Company/Escrow Agent | D41: Caste | G41: Title Name:
B42: h. | C42: Proposed Deed | D42: Caste
B43: i. | C43: Balance Sheet | D43: Caste
B44: j. | C44: Lender's Reserve Requirement (both initial deposit and PUPY amounts) | D44: Caste
B45: k. | C45: Draft Financing Documents | D45: Caste
B46: l. | C46: Lender Term Sheet or Financing Commitment | D46: Caste
B47: m. | C47: LIHTC Documents (if applcable - includes LIHTC lease rider, draft tax credit use agreement, etc.) | D47: N/A
B48: n. | C48: Consent to Assignment of HAP Contract | D48: Caste - Nixon | E48: Is this a pre-consent agreement before executing the assignment? Or consent from lender? | G48: Need confirmation of Fannie, Freddie, or Conventional Financing along with lender name and address
A50: Section 4 | C50: Property Information
B51: a. | C51: Unit count and configuration | D51: Caste
B52: b. | C52: HAP Original Contract | D52: Caste | G52: Limitation on Distributions – Yes/No Reserve for Replacement Requirement – Yes/No
B53: c. | C53: Copies of prior HAP Assignments, if applicable | D53: Caste
B54: d. | C54: HAP Renewal Contract | D54: Caste | G54: Effective Date:
B55: e. | C55: Current Rent Schedule | D55: Caste | G55: Effective Date:
B56: f. | C56: Utility Allowance (if tenant-paid, date of most recent UA baseline) | D56: Caste
B57: g. | C57: Scope of Work | D57: Caste
B58: h. | C58: Relocation Plan, if applicable | D58: N/A
B59: i. | C59: Property Condition Report (PCR) or Project Capital Needs Assessment (PCNA) via the eTool | D59: Caste | E59: From what time period? CNA from 2021, CC will likely do PCR and/or CNA depending on requirements. Needs to be recent and need CNA with Vendor familiar with HUD | G59: Need copy of final report and automated email from HUD confirming the reviewer of the submitted report via HUD’s online eTool
B60: j. | C60: Latest REAC Inspection Report | D60: Caste | G60: REAC Score and Date:
B61: k. | C61: Latest MOR Inspection Report | D61: Caste | G61: MOR Result and Date:
B62: l . | C62: Financial Audits for two previous years | D62: Caste | E62: Have 2023 and 2024, not sure timing of 2025. 2023 and 2024 okay
B63: m. | C63: Interim Financial Statements for the Project (i.e. trailing 12-month) | D63: Caste
B64: n. | C64: Title Commitment | D64: Caste
B65: o. | C65: HUD Use Agreements, if applicable | D65: Caste | E65: Confirm if applicable
B66: p. | C66: Service Coordinator Grant, if applicable | D66: Caste | E66: Confirm if applicable

Sheet Lender Checklist
E3: Northmarq - Lender Checklist
E5: PRIORITY CREDIT ITEMS FOR RATE LOCK | M5: Walker
E6: TBD BORROWING ENTITY | Y6: SENT
E7: 1 | F7: Organizational Chart | G7: Closed | H7: AS | K7: Draft from 1.7.26 | M7: January T-12 Operating Statement (Dec. will suffice)
E8: =+MAX($E7:E$7)+1 -> 2 | F8: Organizational Documents (exec. When available) | G8: Open | H8: AS | K8: RAP UP Partners, LLC OA | M8: Current Rent Roll
E9: =+MAX($E$7:E8)+1 -> 3 | F9: Credit Authorization / Loan History Statement | G9: Open | H9: AS | M9: Schedule of recent Cap Ex repairs (within last two years)
E10: =+MAX($E$7:E9)+1 -> 4 | F10: Current Balance Sheet | G10: Open | H10: AS | M10: Name of proposed management company, summary of their experience, highlighing scattered site and Section 8
M11: Resume/bios for key principals
E12: TBD KEY PRINCIPAL / GUARANTOR | M12: Schedule of REO - unit, occupancy, maturity dates, current lender, noi, market value, DSCR, LTV
E13: =+MAX($E$7:E10)+1 -> 5 | F13: Driver's License or Passport | G13: Open | H13: AS | M13: Financial statements for Caste
E14: =+MAX($E$7:E13)+1 -> 6 | F14: Biography detailing REO & Mgmt Experience | G14: Open | H14: AS
E15: =+MAX($E$7:E14)+1 -> 7 | F15: Credit Authorization / Loan History Statement | G15: Open | H15: AS
E16: =+MAX($E$7:E15)+1 -> 8 | F16: Personal Financial Statements | G16: Open | H16: AS
E17: =+MAX($E$7:E16)+1 -> 9 | F17: RE Schedule and Explanations for all contignecy liabilities | G17: Open | H17: AS
E18: =+MAX($E$7:E17)+1 -> 10 | F18: Verification of Deposits (bank or brokers statements dated within 3 months will suffice) | G18: Open | H18: AS
E20: TBD PRINCIAL INDIVIDUALS
E21: =+MAX($E$7:E18)+1 -> 11 | F21: Driver's License or Passport | G21: Open | H21: AS
E22: =+MAX($E$7:E21)+1 -> 12 | F22: Biography detailing REO & Mgmt Experience | G22: Open | H22: AS
E23: =+MAX($E$7:E22)+1 -> 13 | F23: Credit Authorization / Loan History Statement | G23: Open | H23: AS
E24: =+MAX($E$7:E23)+1 -> 14 | F24: Personal Financial Statements | G24: Open | H24: AS | K24: From Who?
E26: TBD PRINCIPAL ENTITIES
E27: =+MAX($E$7:E24)+1 -> 15 | F27: Organization Documents (exec. When available) | G27: Open | H27: AS
E28: =+MAX($E$7:E27)+1 -> 16 | F28: Credit Authorization / Loan History Statement | G28: Open | H28: AS
E29: =+MAX($E$7:E28)+1 -> 17 | F29: Current Balance Sheet | G29: Open | H29: AS
E31: PROPERTY-LEVEL ITEMS FOR RATE LOCK
E32: OPERATING STATEMENTS
E33: =+MAX($E$7:E32)+1 -> 18 | F33: Historical P&Ls (3 yrs as avail.) | G33: Closed | H33: AS | K33: Uploaded, 2025 thru 11/25
E34: =+MAX($E$7:E33)+1 -> 19 | F34: Current Monthly T-12 | G34: Closed | H34: AS | K34: Included in 18, T-12 from 11/25
E35: =+MAX($E$7:E34)+1 -> 20 | F35: Borrower's Current Budget | G35: Open | H35: AS
E36: =+MAX($E$7:E35)+1 -> 21 | F36: Current Rent Roll(s) (detailed) | G36: Closed | H36: AS | K36: As of 12.31.25
E37: =+MAX($E$7:E36)+1 -> 22 | F37: Collections - 3 months of operating account bank statements for account name to Borrower/Owner | G37: Open | H37: AS
E38: =+MAX($E$7:E37)+1 -> 23 | F38: Collections - Delinquency/Aged Receiveables & Prepaid Report | G38: Closed | H38: AS | K38: As of 12.31.25
E39: =+MAX($E$7:E38)+1 -> 24 | F39: CapEx - Sponsor's recently completed improvements & Lender's receipt of a detailed Cap Ex budget | G39: Open | H39: AS
E40: =+MAX($E$7:E39)+1 -> 25 | F40: Borrower expense comparables for similar properties owned in similar markets (current or prior year P&L data will suffice) | G40: Open | H40: AS
E41: =+MAX($E$7:E40)+1 -> 26 | F41: Property payroll summary | G41: Open | H41: AS
E42: =+MAX($E$7:E41)+1 -> 27 | F42: Cert. of Occ. - if readily available | G42: Closed | H42: AS | K42: 63 Lambert not included
E44: INSURANCE, LEGAL, & THIRD-PARTY ITEMS REQUIRED FOR RATE LOCK
E45: INSURANCE, LEGAL, & THIRD-PARTY ITEMS
E46: =+MAX($E$7:E45)+1 -> 28 | F46: Lender's acceptable insurance review of property and liability insurance policies (inc. Accord 25, 27) and annual premium quote | G46: Open | H46: AS | K46: Getting quote from McGriff, current: Traveler's
E47: =+MAX($E$7:E46)+1 -> 29 | F47: Lender inspection with acceptable findings (acceptable review of corporate units, leases, tenant ledgers, etc.) | G47: Open | H47: AS | I47: Northmarq
E48: =+MAX($E$7:E47)+1 -> 30 | F48: Executed Current Management Contract (or proposed) – explicitly stating compensation. | G48: Open | H48: AS
E49: =+MAX($E$7:E48)+1 -> 31 | F49: ALTA Survey / Title Policy Commitment | G49: Open | H49: AS | K49: ALTA expected mid-March, 6 weeks from release
E50: =+MAX($E$7:E49)+1 -> 32 | F50: Acceptable Review of: Appraisal | G50: Open | H50: AS | I50: Northmarq
E51: =+MAX($E$7:E50)+1 -> 33 | F51: Acceptable Review of: PCA and Enviro Report indications including approach to radon testing and mitigation, required O&M reports, and WDI report, if needed | G51: Open | H51: AS | K51: EBI, mid-March, 6 weeks from release
E52: =+MAX($E$7:E51)+1 -> 34 | F52: Acceptable Review of: Lender's review of zoning report | G52: Open | H52: AS | I52: Northmarq
E53: =+MAX($E$7:E52)+1 -> 35 | F53: Good Faith Deposit Confirmation | G53: Open | H53: AS
E54: =+MAX($E$7:E53)+1 -> 36 | F54: Title Company / Escrow Agent receipts and disbursements ledger for the transaction showing: Source of all funds deposited (with federal fund wires and full entity names) in the closing escrow) The flow of all funds disbursed from the closing escrow to the Mortage Loan | G54: Open | H54: AS
E55: =+MAX($E$7:E54)+1 -> 37 | F55: Fannie Mae approval of Loan Doc Mods (if any) | G55: Open | H55: AS
E56: =+MAX($E$7:E55)+1 -> 38 | F56: UCC/Tax Lien/Judgement Searchs - for Borrowing entite, key principals, guarantor (will be ordered by Lender Counsel) | G56: Open | H56: AS
E57: =+MAX($E$7:E56)+1 -> 39 | F57: Additional RL items noted in Legal check list | G57: Open | H57: AS
E58: =+MAX($E$7:E57)+1 -> 40 | F58: Copy of Current Note and Payoff Letter | G58: Open | H58: AS
E59: =+MAX($E$7:E58)+1 -> 41 | F59: Underwriting Certificate (will be prepared for signatures at a later date) | G59: Open | H59: AS
E61: OTHER ITEMS REQUIRED FOR CLOSING
E62: OTHER
E63: =+MAX($E$7:E62)+1 -> 42 | F63: W-9 Tax Identification Certification - for Borrowing Entity | G63: Open | H63: AS
E64: =+MAX($E$7:E63)+1 -> 43 | F64: Preliminary Estimate of Sources and Uses | G64: Open | H64: AS
E65: =+MAX($E$7:E64)+1 -> 44 | F65: ACH Form & Voided Check - for Borrowing Entity | G65: Open | H65: AS

Sheet Deal Team
B2: Role | C2: Organization | D2: Name
B3: Acquiror | C3: Caste Capital | D3: Bode Adunbarin
B4: Acquiror | C4: Caste Capital | D4: David Stewart
B5: Acquiror | C5: Caste Capital | D5: Patrick Kimble
B6: Acquiror | C6: Caste Capital | D6: Alex Schultz
B7: Acquiror | C7: Menkiti Group | D7: Bo Menkiti
B8: Acquiror | C8: Menkiti Group | D8: John Daniels
B9: Acquiror/Seller | C9: Catalyst Ventures | D9: Darryl Settles
B10: Broker | C10: Colliers | D10: Jeanne Pinnado
B11: Legal Counsel | C11: Nixon Peabody | D11: Alex Rosso
B12: HAP Contract Administrator | C12: MassHousing | D12: TBC
B13: 3P - Physical Needs Assessor | C13: TBC | D13: TBC
... B24: Debt Financing (Option) | C24: LISC | D24: Gustavo Quiroga

Sheet Cost Schedule
B2: DD SCHEDULE / COST TRACKER
C4: Phase | D4: Task | E4: Party | F4: Start | G4: Duration | H4: End | I4: Budget | J4: Proposal Cost | K4: Spent | L4: Remaining | O4: 46013 | P4: =+EOMONTH(O4,1) -> 46053 | Q4: =+EOMONTH(P4,1) -> 46081 | R4: =+EOMONTH(Q4,1) -> 46112 | S4: =+EOMONTH(R4,1) -> 46142 | T4: =+EOMONTH(S4,1) -> 46173 | U4: =+EOMONTH(T4,1) -> 46203 | V4: =+EOMONTH(U4,1) -> 46234 | W4: =+EOMONTH(V4,1) -> 46265 | X4: =+EOMONTH(W4,1) -> 46295 | Z4: CHECK
C5: Acquisition - Legal | D5: Execute LOI | E5: Acquiror/Seller | F5: 46013 | G5: 0 | H5: =+F5+G5 -> 46013 | I5: 0.0001 | J5: 0.0001 | K5: 0.0001 | L5: =+J5-K5 -> 0 | O5: =+IF(AND(O$4>=$F5,O$4<=$H5),$J5,0) -> 0.0001 | P5: =+IF(AND(P$4>=$F5,P$4<=$H5),$J5,0) -> 0 | Q5: =+IF(AND(Q$4>=$F5,Q$4<=$H5),$J5,0) -> 0 | R5: =+IF(AND(R$4>=$F5,R$4<=$H5),$J5,0) -> 0 | S5: =+IF(AND(S$4>=$F5,S$4<=$H5),$J5,0) -> 0 | T5: =+IF(AND(T$4>=$F5,T$4<=$H5),$J5,0) -> 0 | U5: =+IF(AND(U$4>=$F5,U$4<=$H5),$J5,0) -> 0 | V5: =+IF(AND(V$4>=$F5,V$4<=$H5),$J5,0) -> 0 | ... X5: =+IF(AND(X$4>=$F5,X$4<=$H5),$J5,0) -> 0 | Z5: =+SUM(O5:X5)-J5 -> 0
C6: Acquisition - Legal | D6: Draft and execute PSA | E6: Acquiror | F6: =+$H$5 -> 46013 | G6: 40 | H6: =+F6+G6 -> 46053 | I6: 7500 | J6: 7500 | K6: 0 | L6: =+J6-K6 -> 7500 | O6: 0 | P6: 0 | Q6: 0 | R6: 0 | S6: 0 | T6: =+$J6 -> 7500 | U6: 0 | V6: 0 | W6: 0 | X6: 0 | Z6: =+SUM(O6:X6)-J6 -> 0
C7: Acquisition - Legal | D7: Draft and execute LPA, JVAs | E7: Acquiror/Seller/Nixon | F7: =+$H$5 -> 46013 | G7: 40 | H7: =+F7+G7 -> 46053 | I7: 10000 | J7: 10000 | K7: 0 | L7: =+J7-K7 -> 10000 | O7: 0 | P7: 0 | Q7: 0 | R7: 0 | S7: 0 | T7: =+$J7 -> 10000 | U7: 0 | V7: 0 | W7: 0 | X7: 0 | Z7: =+SUM(O7:X7)-J7 -> 0
C8: Acquisition - Legal | D8: Draft and execute Caste GP formation doc | E8: CC, Nixon | F8: =+$H$5 -> 46013 | G8: 40 | H8: =+F8+G8 -> 46053 | I8: 2500 | J8: 2500 | K8: 0 | L8: =+J8-K8 -> 2500 | O8: 0 | P8: 0 | Q8: 0 | R8: 0 | S8: 0 | T8: =+$J8 -> 2500 | U8: 0 | V8: 0 | W8: 0 | X8: 0 | Z8: =+SUM(O8:X8)-J8 -> 0
C9: DD / HUD Approvals | D9: Mgmt agent and ownership approvals, HAP Contract Review & Assumption | E9: Acquiror, Seller, Nixon Peabody, MassHousing | F9: =+$H$6 -> 46053 | G9: =60+60 -> 120 | H9: =+F9+G9 -> 46173 | I9: 35000 | J9: 35000 | K9: 0 | L9: =+J9-K9 -> 35000 | O9: =+IF(AND(O$4>=$F9,O$4<=$H9),$J9,0) -> 0 | P9: 0 | Q9: 0 | R9: 0 | S9: 0 | T9: =+$J9 -> 35000 | U9: 0 | V9: 0 | W9: 0 | X9: 0 | Z9: =+SUM(O9:X9)-J9 -> 0
C10: Acquisition - Legal | D10: Draft and execute PMAs | E10: Acquiror/Seller/Nixon | F10: =+$H$5 -> 46013 | G10: 40 | H10: =+F10+G10 -> 46053 | I10: 12500 | J10: 12500 | K10: 0 | L10: =+J10-K10 -> 12500 | O10: 0 | P10: 0 | Q10: 0 | R10: 0 | S10: 0 | T10: =+$J10 -> 12500 | U10: 0 | V10: 0 | W10: 0 | X10: 0 | Z10: =+SUM(O10:X10)-J10 -> 0
C11: Due Diligence | D11: Zoning Certificate / Letter | E11: Acquiror, 3Ps | F11: =+$H$6+1 -> 46054 | G11: 60 | H11: =+F11+G11 -> 46114 | I11: 5000 | J11: 0 | K11: 0 | L11: =+J11-K11 -> 0 | O11: 0 | P11: 0 | Q11: 0 | R11: 0 | S11: 0 | T11: =+$J11 -> 0 | U11: 0 | V11: 0 | W11: 0 | X11: 0 | Z11: =+SUM(O11:X11)-J11 -> 0
C12: Due Diligence | D12: Title Review | E12: Acquiror, 3Ps | F12: =+$H$6+1 -> 46054 | G12: 60 | H12: =+F12+G12 -> 46114 | I12: 5000 | J12: 5000 | K12: 0 | L12: =+J12-K12 -> 5000 | O12: 0 | P12: 0 | Q12: 0 | R12: 0 | S12: 0 | T12: =+$J12 -> 5000 | U12: 0 | V12: 0 | W12: 0 | X12: 0 | Z12: =+SUM(O12:X12)-J12 -> 0
C13: Due Diligence | D13: Order ALTA Survey | E13: Acquiror, 3Ps | F13: =+$H$6+1 -> 46054 | G13: 60 | H13: =+F13+G13 -> 46114 | I13: 45000 | J13: 40000 | K13: 0 | L13: =+J13-K13 -> 40000 | O13: 0 | P13: 0 | Q13: 0 | R13: 0 | S13: 0 | T13: =+$J13 -> 40000 | U13: 0 | V13: 0 | W13: 0 | X13: 0 | Z13: =+SUM(O13:X13)-J13 -> 0
C14: Due Diligence | D14: Order PCA/CNA | E14: Acquiror, 3Ps | F14: =+$H$6+1 -> 46054 | G14: 60 | H14: =+F14+G14 -> 46114 | I14: =60000 -> 60000 | J14: 8050 | K14: 0 | L14: =+J14-K14 -> 8050 | O14: 0 | P14: 0 | Q14: 0 | R14: =+$J14*0.75 -> 6037.5 | S14: =+$J14*0.25 -> 2012.5 | T14: 0 | U14: 0 | V14: 0 | W14: 0 | X14: 0 | Z14: =+SUM(O14:X14)-J14 -> 0
C15: Due Diligence | D15: Phase I ESA | E15: Acquiror, 3Ps | F15: =+$H$6+1 -> 46054 | G15: 60 | H15: =+F15+G15 -> 46114 | I15: =60000 -> 60000 | J15: 13200 | K15: 0 | L15: =+J15-K15 -> 13200 | O15: 0 | P15: 0 | Q15: 0 | R15: =+$J15*0.75 -> 9900 | S15: =+$J15*0.25 -> 3300 | T15: 0 | U15: 0 | V15: 0 | W15: 0 | X15: 0 | Z15: =+SUM(O15:X15)-J15 -> 0
C16: Due Diligence | D16: Misc | E16: Acquiror, 3Ps | F16: =+$H$6+1 -> 46054 | G16: 60 | H16: =+F16+G16 -> 46114 | I16: 5000 | J16: 0 | K16: 0 | L16: =+J16-K16 -> 0 | O16: 0 | P16: 0 | Q16: 0 | R16: 0 | S16: 0 | T16: =+$J16 -> 0 | U16: 0 | V16: 0 | W16: 0 | X16: 0 | Z16: =+SUM(O16:X16)-J16 -> 0
C17: Due Diligence | D17: Rent Comp Study | E17: Acquiror, APR | F17: =+$H$6 -> 46053 | G17: 45 | H17: =+F17+G17 -> 46098 | I17: 0 | J17: 7000 | K17: 0 | L17: =+J17-K17 -> 7000 | O17: 0 | P17: 0 | Q17: =+$J17 -> 7000 | R17: 0 | S17: 0 | T17: 0 | U17: 0 | V17: 0 | W17: 0 | X17: 0 | Z17: =+SUM(O17:X17)-J17 -> 0
C18: Due Diligence | D18: 2530 Clearance Work | E18: Acquiror, APR | F18: =+$H$6 -> 46053 | G18: 45 | H18: =+F18+G18 -> 46098 | I18: 0 | J18: 7500 | K18: 0 | L18: =+J18-K18 -> 7500 | O18: 0 | P18: 0 | Q18: 0 | R18: =+$J18*0.5 -> 3750 | S18: =+$J18*0.5 -> 3750 | T18: 0 | U18: 0 | V18: 0 | W18: 0 | X18: 0 | Z18: =+SUM(O18:X18)-J18 -> 0
C19: Due Diligence | D19: Ryan Tax Report | E19: Acquiror, 3Ps | F19: =+$H$6+1 -> 46054 | G19: 60 | H19: =+F19+G19 -> 46114 | I19: 0 | J19: 2000 | K19: 0 | L19: =+J19-K19 -> 2000 | O19: 0 | P19: 0 | Q19: 0 | R19: =+$J19 -> 2000 | S19: 0 | T19: 0 | U19: 0 | V19: 0 | W19: 0 | X19: 0 | Z19: =+SUM(O19:X19)-J19 -> 0
C20: Financing | D20: Lender legal fees | E20: Acquiror, Lender, Nixon | F20: =+$H$6+1 -> 46054 | G20: 60 | H20: =+F20+G20 -> 46114 | I20: 27000 | J20: 15000 | K20: 0 | L20: =+J20-K20 -> 15000 | O20: 0 | P20: 0 | Q20: 0 | R20: =+$J20 -> 15000 | S20: 0 | T20: 0 | U20: 0 | V20: 0 | W20: 0 | X20: 0 | Z20: =+SUM(O20:X20)-J20 -> 0
C21: Financing | D21: Lender Reports & fees | E21: Acquiror, Lender, Nixon | F21: =+$H$6+1 -> 46054 | G21: 60 | H21: =+F21+G21 -> 46114 | I21: 20000 | J21: =15000+13000 -> 28000 | K21: 0 | L21: =+J21-K21 -> 28000 | O21: 0 | P21: 0 | Q21: 0 | R21: =+$J21 -> 28000 | S21: 0 | T21: 0 | U21: 0 | V21: 0 | W21: 0 | X21: 0 | Z21: =+SUM(O21:X21)-J21 -> 0
C22: Due Diligence | D22: Affordable consultant | E22: Acquiror, Jacques | F22: =+F9 -> 46053 | G22: =+G9 -> 120 | H22: =+F22+G22 -> 46173 | I22: =50500 -> 50500 | J22: =+I22 -> 50500 | K22: 0 | L22: =+J22-K22 -> 50500 | O22: 0 | P22: 0 | Q22: 0 | R22: 0 | S22: 0 | T22: =+$J22 -> 50500 | U22: 0 | V22: 0 | W22: 0 | X22: 0 | Z22: =+SUM(O22:X22)-J22 -> 0
C23: Contingency | F23: =+$H$5 -> 46013 | G23: 40 | H23: =+F23+G23 -> 46053 | I23: 0 | J23: =10%*SUM(J5:J22,-J22) -> 19325 | K23: 0 | L23: =+J23-K23 -> 19325 | O23: 0 | P23: 0 | Q23: 0 | R23: 0 | S23: 0 | T23: =+$J23 -> 19325 | U23: 0 | V23: 0 | W23: 0 | X23: 0 | Z23: =+SUM(O23:X23)-J23 -> 0
C24: Deposit #1 | D24: Escrow deposit ($50K at PSA signing) | E24: Acquiror | F24: =+$H$6 -> 46053 | G24: 5 | H24: =+F24+G24 -> 46058 | I24: 50000 | J24: =+I24 -> 50000 | K24: 0 | L24: =+J24-K24 -> 50000 | O24: 0 | P24: 0 | Q24: =+$J24 -> 50000 | R24: 0 | S24: 0 | T24: 0 | U24: 0 | V24: 0 | W24: 0 | X24: 0 | Z24: =+SUM(O24:X24)-J24 -> 0
C25: Deposit #2 | D25: Escrow deposit ($150K at DD) | E25: Acquiror | F25: =+$H$6+60 -> 46113 | G25: 5 | H25: =+F25+G25 -> 46118 | I25: 150000 | J25: =+I25 -> 150000 | K25: 0 | L25: =+J25-K25 -> 150000 | O25: 0 | P25: 0 | Q25: 0 | R25: 0 | S25: =+$J25 -> 150000 | T25: 0 | U25: 0 | V25: 0 | W25: 0 | X25: 0 | Z25: =+SUM(O25:X25)-J25 -> 0
C26: Total (Incl. Deposits) | I26: =SUM(I5:I25) -> 545000 | J26: =SUM(J5:J25) -> 463075 | K26: =SUM(K5:K25) -> 0.0001 | O26: =SUM(O5:O25) -> 0.0001 | P26: =SUM(P5:P25) -> 0 | Q26: =SUM(Q5:Q25) -> 57000 | R26: =SUM(R5:R25) -> 64687.5 | S26: =SUM(S5:S25) -> 159062.5 | T26: =SUM(T5:T25) -> 182325 | U26: =SUM(U5:U25) -> 0 | V26: =SUM(V5:V25) -> 0 | ... X26: =SUM(X5:X25) -> 0 | Z26: =+SUM(O26:X26)-J26 -> 0
C27: Total (Excl. Deposits) | I27: =+I26-SUM(I25,I24) -> 345000 | J27: =+J26-SUM(J25,J24) -> 263075 | K27: =+K26-SUM(K25,K24) -> 0.0001 | O27: =+O26-SUM(O25,O24) -> 0.0001 | P27: =+P26-SUM(P25,P24) -> 0 | Q27: =+Q26-SUM(Q25,Q24) -> 7000 | R27: =+R26-SUM(R25,R24) -> 64687.5 | S27: =+S26-SUM(S25,S24) -> 9062.5 | T27: =+T26-SUM(T25,T24) -> 182325 | U27: =+U26-SUM(U25,U24) -> 0 | V27: =+V26-SUM(V25,V24) -> 0 | ... X27: =+X26-SUM(X25,X24) -> 0 | Z27: =+SUM(O27:X27)-J27 -> 0
C29: Note: | P29: =+P26*50% -> 0 | Q29: =+Q26*50% -> 28500 | R29: =+R26*50% -> 32343.75 | S29: =+S26*50% -> 79531.25 | T29: =+T26*50% -> 91162.5
C30: Dates are approximations. | P30: =+P27*50% -> 0 | Q30: =+Q27*50% -> 3500 | R30: =+R27*50% -> 32343.75 | S30: =+S27*50% -> 4531.25 | T30: =+T27*50% -> 91162.5
P31: =+P30/4 -> 0 | Q31: =+Q30/4 -> 875 | R31: =+R30/4 -> 8085.9375 | S31: =+S30/4 -> 1132.8125 | T31: =+T30/4 -> 22790.625

Sheet External - DD List
D2: DUE DILIGENCE REQUEST LIST | F2: 45992
D3: RAP UP Portfolio
I4: =+TODAY() -> 46217
C5: DIV Folder | D5: Item # | E5: Document | F5: Status | G5: Department | H5: Responsible Party | I5: DIV Comment | J5: Partner Comment
D6: LEASING & MARKETING
D7: =+MAX($D$5:D5)+1 -> 1 | E7: Residential Leases & House Rules | F7: Open | G7: Leasing / Marketing
D8: =+MAX($D$5:D7)+1 -> 2 | E8: License Agreements (if applicable) | F8: Open | G8: Leasing / Marketing
D9: =+MAX($D$5:D8)+1 -> 3 | E9: Indemnities (if applicable) | F9: Open | G9: Leasing / Marketing
D10: PHYSICAL / PROPERTY
E11: Title and Zoning | F11: Open | G11: Development
D12: =+MAX($D$5:D11)+1 -> 4 | E12: ALTA Survey | F12: Open | G12: Development
D13: =+MAX($D$5:D12)+1 -> 5 | E13: Existing Title Insurance Policy | F13: Open | G13: Development
D14: =+MAX($D$5:D13)+1 -> 6 | E14: Deleted | F14: Deleted | G14: Deleted
D15: =+MAX($D$5:D14)+1 -> 7 | E15: All City/State permits | F15: Open | G15: Development
D16: =+MAX($D$5:D15)+1 -> 8 | E16: Easement Documents (if applicable) | F16: Open | G16: Development
D17: =+MAX($D$5:D16)+1 -> 9 | E17: Confirm FEMA Flood Vulnerable Status | F17: Open | G17: Development
D18: =+MAX($D$5:D17)+1 -> 10 | E18: Permits Required for Property Operation (e.g. flammable fuel storage) | F18: Open | G18: Development
E19: Environmental Information
D20: =+MAX($D$5:D19)+1 -> 11 | E20: Phase 1 and 2 ESA | F20: Open | G20: Development
D21: =+MAX($D$5:D20)+1 -> 12 | E21: Hazardous Materials report | F21: Open | G21: Development
D22: =+MAX($D$5:D21)+1 -> 13 | E22: Geotechnical soils report | F22: Open | G22: Development
D23: =+MAX($D$5:D22)+1 -> 14 | E23: Lead abatement/compliance report | F23: Open | G23: Development
D24: =+MAX($D$5:D23)+1 -> 15 | E24: Mold reports/remediation | F24: Open | G24: Development
D25: =+MAX($D$5:D24)+1 -> 16 | E25: Indoor air quality reports | F25: Open | G25: Development
D26: =+MAX($D$5:D25)+1 -> 17 | E26: Water intrusion/moisture issues | F26: Open | G26: Development
D27: =+MAX($D$5:D26)+1 -> 18 | E27: Deleted | F27: Deleted | G27: Deleted
D28: =+MAX($D$5:D27)+1 -> 19 | E28: Deleted | F28: Deleted | G28: Deleted
E29: Drawings
D30: =+MAX($D$5:D29)+1 -> 20 | E30: Site Plans/Building Plans / Construction Plans / As-Builts | F30: Open | G30: Development
D31: =+MAX($D$5:D30)+1 -> 21 | E31: Building Permits | F31: Open | G31: Development
D32: =+MAX($D$5:D31)+1 -> 22 | E32: Certificates of Occupancy | F32: Open | G32: Development
D33: =+MAX($D$5:D32)+1 -> 23 | E33: Building areas - Building GSF, Unit RSF's | F33: Open | G33: Development
D34: =+MAX($D$5:D33)+1 -> 24 | E34: Deleted | F34: Deleted | G34: Deleted
D35: =+MAX($D$5:D34)+1 -> 25 | E35: REAC reports and scores from prior 3 years | F35: Open | G35: Development
D36: =+MAX($D$5:D35)+1 -> 26 | E36: Capital Needs Assessment | F36: Open | G36: Development
D37: PROPERTY MANAGEMENT
D38: =+MAX($D$5:D36)+1 -> 27 | E38: 2026 Operating Budget | F38: Open | G38: Prop Mgmt
D39: =+MAX($D$5:D38)+1 -> 28 | E39: Management & Occupancy Review past 3 years
D40: =+MAX($D$5:D39)+1 -> 29 | E40: Personal Property Inventory | F40: Open | G40: Prop Mgmt
D41: =+MAX($D$5:D40)+1 -> 30 | E41: Photographs | F41: Open | G41: Prop Mgmt
D42: =+MAX($D$5:D41)+1 -> 31 | E42: Physical Reports / Property Condition Reports | F42: Open | G42: Prop Mgmt
D43: =+MAX($D$5:D42)+1 -> 32 | E43: Roof Reports/Repairs/Maintenance | F43: Open | G43: Prop Mgmt
D44: =+MAX($D$5:D43)+1 -> 33 | E44: Structural & Seismic Reports | F44: Open | G44: Prop Mgmt
D45: =+MAX($D$5:D44)+1 -> 34 | E45: Work Orders/PM Logs (HVAC, R&M, Roof, etc.) | F45: Open | G45: Prop Mgmt
D46: =+MAX($D$5:D45)+1 -> 35 | E46: Deleted | F46: Deleted | G46: Deleted
D47: =+MAX($D$5:D46)+1 -> 36 | E47: Deleted | F47: Deleted | G47: Deleted
D48: =+MAX($D$5:D47)+1 -> 37 | E48: Service Agreements (list) | F48: Open | G48: Prop Mgmt
D49: =+MAX($D$5:D48)+1 -> 38 | E49: Warranties (list) | F49: Open | G49: Prop Mgmt
D50: =+MAX($D$5:D49)+1 -> 39 | E50: Vendor Contact List | F50: Open | G50: Prop Mgmt
D51: =+MAX($D$5:D50)+1 -> 40 | E51: Utility Account Numbers List & Identification | F51: Open | G51: Prop Mgmt
... D60: =+MAX($D$5:D59)+1 -> 49 | E60: Deleted | F60: Deleted | G60: Deleted
D61: AFFORDABLE
D62: =+MAX($D$5:D60)+1 -> 50 | E62: Sample 50059 files including one current resident with recertification and one former tenant | F62: Open | G62: Prop Mgmt
D63: =+MAX($D$5:D62)+1 -> 51 | E63: Original HAP Contract | F63: Open | G63: Prop Mgmt
D64: =+MAX($D$5:D63)+1 -> 52 | E64: HAP Billing Files (HUD 52670A) - YTD and prior year | F64: Open
D65: =+MAX($D$5:D64)+1 -> 53 | E65: Tenant Selection Plan | F65: Open | G65: Prop Mgmt
D66: =+MAX($D$5:D65)+1 -> 54 | E66: Affirmative Fair Housing Marketing Plan | F66: Open | G66: Prop Mgmt
D67: =+MAX($D$5:D66)+1 -> 55 | E67: Enterprise Income Verification (EIV) Master File | F67: Open
D68: =+MAX($D$5:D67)+1 -> 56 | E68: Extended Use Agreement (if applicable) | F68: Open | G68: Prop Mgmt
D69: =+MAX($D$5:D68)+1 -> 57 | E69: Current Waitlist | F69: Open | G69: Prop Mgmt
D70: =+MAX($D$5:D69)+1 -> 58 | E70: Recent Management and Occupancy Review (MOR) reports from last 3 years | F70: Open | G70: Prop Mgmt
D71: =+MAX($D$5:D70)+1 -> 59 | E71: Any non-compliance agency or audit findings from last 3 years | F71: Open | G71: Prop Mgmt
D72: LEGAL, INSURANCE AND TAX DOCUMENTS
D73: =+MAX($D$5:D71)+1 -> 60 | E73: Insurance Policies/Summary Docs/Exclusions | F73: Open | G73: Legal/Ins/Tax
D74: =+MAX($D$5:D73)+1 -> 61 | E74: Summary of Litigation Pending or in Progress | F74: Open | G74: Legal/Ins/Tax
D75: =+MAX($D$5:D74)+1 -> 62 | E75: Summary of Outstanding Insurance Claims | F75: Open | G75: Legal/Ins/Tax
D76: =+MAX($D$5:D75)+1 -> 63 | E76: Tax Appeals / Reduction History | F76: Open | G76: Legal/Ins/Tax
D77: =+MAX($D$5:D76)+1 -> 64 | E77: Tax Bills YTD + 3 prior years (including unsecured personal property) | F77: Open | G77: Legal/Ins/Tax
D78: =+MAX($D$5:D77)+1 -> 65 | E78: Total Insured Value (TIV) / Claims and Loss History - prior 3 years | F78: Open | G78: Legal/Ins/Tax
D79: =+MAX($D$5:D78)+1 -> 66 | E79: Property Management Agreement | F79: Open | G79: Legal/Ins/Tax
D80: ACCOUNTING / FINANCE
D81: =+MAX($D$5:D80)+1 -> 67 | E81: Aged Receivable / Delinquency Report YTD (update if available) + 3 prior years | F81: Open | G81: Accounting
D82: =+MAX($D$5:D81)+1 -> 68 | E82: Appraisals | F82: Open | G82: Accounting
D83: =+MAX($D$5:D82)+1 -> 69 | E83: Detailed Operating Budget YTD + 3 prior years | F83: Open | G83: Accounting
D84: =+MAX($D$5:D83)+1 -> 70 | E84: Capital Expenditures - Historical (3 prior years) & 2026 Budget | F84: Open | G84: Accounting
D85: =+MAX($D$5:D84)+1 -> 71 | E85: Deferred Maintenance | F85: Open | G85: Accounting
D86: =+MAX($D$5:D85)+1 -> 72 | E86: Rent Statements YTD + 3 prior years | F86: Open | G86: Accounting
D87: =+MAX($D$5:D86)+1 -> 73 | E87: Security Deposits Schedule | F87: Open | G87: Accounting
D88: =+MAX($D$5:D87)+1 -> 74 | E88: Tenant Billing Register YTD + 3 prior years | F88: Open | G88: Accounting
D89: =+MAX($D$5:D88)+1 -> 75 | E89: Utility Bills - 12 months | F89: Open | G89: Accounting
D90: =+MAX($D$5:D89)+1 -> 76 | E90: Vendor Bills - 3 prior years | F90: Open | G90: Accounting
J65527: still need
